Metadata-Version: 2.1
Name: convergence-api
Version: 0.1.1
Summary: A simple, easy to use wrapper for Elavon's Converge API via key value pairs instead of XML
Home-page: http://github.com/wontonst/python-convergence-api
Author: Roy Zheng
License: MIT
Platform: UNKNOWN
